<?xml version="1.0" encoding="utf-8" ?>
<blocks>
    <andesite>
        <andesite name="Andesite" icon="andesite"/>
        <andesite_stairs name="Andesite&#xA;Stairs" icon="andesite_stairs"/>
        <andesite_slab name="Andesite&#xA;Slab" icon="andesite_slab"/>
        <andesite_wall name="Andesite&#xA;Wall" icon="andesite_wall"/>
        <polished_andesite name="Polished&#xA;Andesite" icon="polished_andesite"/>
        <polished_andesite_stairs name="Polished&#xA;Andesite&#xA;Stairs" icon="polished_andesite_stairs"/>
        <polished_andesite_slab name="Polished&#xA;Andesite&#xA;Slab" icon="polished_andesite_slab"/>
    </andesite>
    <banners>
        <white_banner name="White&#xA;Banner" icon="white_banner" tags="wool"/>
        <red_banner name="Red&#xA;Banner" icon="red_banner" tags="wool"/>
        <orange_banner name="Orange&#xA;Banner" icon="orange_banner" tags="wool"/>
        <yellow_banner name="Yellow&#xA;Banner" icon="yellow_banner" tags="wool"/>
        <lime_banner name="Lime&#xA;Banner" icon="lime_banner" tags="wool"/>
        <green_banner name="Green&#xA;Banner" icon="green_banner" tags="wool"/>
        <cyan_banner name="Cyan&#xA;Banner" icon="cyan_banner" tags="wool"/>
        <light_blue_banner name="Light Blue&#xA;Banner" icon="light_blue_banner" tags="wool"/>
        <blue_banner name="Blue&#xA;Banner" icon="blue_banner" tags="wool"/>
        <purple_banner name="Purple&#xA;Banner" icon="purple_banner" tags="wool"/>
        <magenta_banner name="Magenta&#xA;Banner" icon="magenta_banner" tags="wool"/>
        <pink_banner name="Pink&#xA;Banner" icon="pink_banner" tags="wool"/>
        <brown_banner name="Brown&#xA;Banner" icon="brown_banner" tags="wool"/>
        <light_gray_banner name="Light Gray&#xA;Banner" icon="light_gray_banner" tags="wool"/>
        <gray_banner name="Gray&#xA;Banner" icon="gray_banner" tags="wool"/>
        <black_banner name="Black&#xA;Banner" icon="black_banner" tags="wool"/>
    </banners>
    <beds>
        <white_bed name="White Bed" icon="white_bed" tags="wool"/>
        <red_bed name="Red Bed" icon="red_bed" tags="wool"/>
        <orange_bed name="Orange Bed" icon="orange_bed" tags="wool"/>
        <yellow_bed name="Yellow Bed" icon="yellow_bed" tags="wool"/>
        <lime_bed name="Lime Bed" icon="lime_bed" tags="wool"/>
        <green_bed name="Green Bed" icon="green_bed" tags="wool"/>
        <cyan_bed name="Cyan Bed" icon="cyan_bed" tags="wool"/>
        <light_blue_bed name="Light Blue&#xA;Bed" icon="light_blue_bed" tags="wool"/>
        <blue_bed name="Blue Bed" icon="blue_bed" tags="wool"/>
        <purple_bed name="Purple Bed" icon="purple_bed" tags="wool"/>
        <magenta_bed name="Magenta Bed" icon="magenta_bed" tags="wool"/>
        <pink_bed name="Pink Bed" icon="pink_bed" tags="wool"/>
        <brown_bed name="Brown Bed" icon="brown_bed" tags="wool"/>
        <light_gray_bed name="Light Gray&#xA;Bed" icon="light_gray_bed" tags="wool"/>
        <gray_bed name="Gray Bed" icon="gray_bed" tags="wool"/>
        <black_bed name="Black Bed" icon="black_bed" tags="wool"/>
    </beds>
    <blackstone>
        <blackstone name="Blackstone" icon="blackstone"/>
        <gilded_blackstone name="Gilded Blackstone" icon="gilded_blackstone" tags="silktouch"/>
        <blackstone_stairs name="Blackstone Stairs" icon="blackstone_stairs"/>
        <blackstone_slab name="Blackstone Slab" icon="blackstone_slab"/>
        <blackstone_wall name="Blackstone Wall" icon="blackstone_wall"/>
        <polished_blackstone_bricks name="Polished Blackstone Bricks" icon="polished_blackstone_bricks"/>
        <cracked_polished_blackstone_bricks name="Cracked Blackstone Bricks" icon="cracked_polished_blackstone_bricks"/>
        <polished_blackstone_brick_stairs name="Blackstone Brick Stairs" icon="polished_blackstone_brick_stairs"/>
        <polished_blackstone_brick_slab name="Polished Blackstone Brick Slab" icon="polished_blackstone_brick_slab"/>
        <polished_blackstone_brick_wall name="Polished Blackstone Wall" icon="polished_blackstone_brick_wall"/>
        <chiseled_polished_blackstone name="Chiseled Polished Blackstone" icon="chiseled_polished_blackstone"/>
        <polished_blackstone name="Polished Blackstone" icon="polished_blackstone"/>
        <polished_blackstone_stairs name="Polished Blackstone Stairs" icon="polished_blackstone_stairs"/>
        <polished_blackstone_slab name="Polished Blackstone Slab" icon="polished_blackstone_slab"/>
        <polished_blackstone_wall name="Polished Blackstone Wall" icon="polished_blackstone_wall"/>
    </blackstone>
    <bricks>
        <bricks name="Bricks" icon="bricks"/>
        <brick_wall name="Brick Wall" icon="brick_wall"/>
        <brick_stairs name="Brick Stairs" icon="brick_stairs"/>
        <brick_slab name="Brick Slab" icon="brick_slab"/>
    </bricks>
    <carpet>
        <white_carpet name="White&#xA;Carpet" icon="white_carpet" tags="wool"/>
        <red_carpet name="Red&#xA;Carpet" icon="red_carpet" tags="wool"/>
        <orange_carpet name="Orange&#xA;Carpet" icon="orange_carpet" tags="wool"/>
        <yellow_carpet name="Yellow&#xA;Carpet" icon="yellow_carpet" tags="wool"/>
        <lime_carpet name="Lime&#xA;Carpet" icon="lime_carpet" tags="wool"/>
        <green_carpet name="Green&#xA;Carpet" icon="green_carpet" tags="wool"/>
        <cyan_carpet name="Cyan&#xA;Carpet" icon="cyan_carpet" tags="wool"/>
        <light_blue_carpet name="Light Blue&#xA;Carpet" icon="light_blue_carpet" tags="wool"/>
        <blue_carpet name="Blue&#xA;Carpet" icon="blue_carpet" tags="wool"/>
        <purple_carpet name="Purple&#xA;Carpet" icon="purple_carpet" tags="wool"/>
        <magenta_carpet name="Magenta&#xA;Carpet" icon="magenta_carpet" tags="wool"/>
        <pink_carpet name="Pink&#xA;Carpet" icon="pink_carpet" tags="wool"/>
        <brown_carpet name="Brown&#xA;Carpet" icon="brown_carpet" tags="wool"/>
        <light_gray_carpet name="Light Gray&#xA;Carpet" icon="light_gray_carpet" tags="wool"/>
        <gray_carpet name="Gray&#xA;Carpet" icon="gray_carpet" tags="wool"/>
        <black_carpet name="Black&#xA;Carpet" icon="black_carpet" tags="wool"/>
    </carpet>
    <candles>
        <candle              name="Candle"                     icon="candle" tags="beewax beeswax"/>
        <white_candle        name="White&#xA;Candle"           icon="white_candle" tags="beewax beeswax"/>
        <red_candle          name="Red&#xA;Candle"             icon="red_candle" tags="beewax beeswax"/>
        <orange_candle       name="Orange&#xA;Candle"          icon="orange_candle" tags="beewax beeswax"/>
        <yellow_candle       name="Yellow&#xA;Candle"          icon="yellow_candle" tags="beewax beeswax"/>
        <lime_candle         name="Lime&#xA;Candle"            icon="lime_candle" tags="beewax beeswax"/>
        <green_candle        name="Green&#xA;Candle"           icon="green_candle" tags="beewax beeswax"/>
        <cyan_candle         name="Cyan&#xA;Candle"            icon="cyan_candle" tags="beewax beeswax"/>
        <light_blue_candle   name="Light Blue&#xA;Candle"      icon="light_blue_candle" tags="beewax beeswax"/>
        <blue_candle         name="Blue&#xA;Candle"            icon="blue_candle" tags="beewax beeswax"/>
        <purple_candle       name="Purple&#xA;Candle"          icon="purple_candle" tags="beewax beeswax"/>
        <magenta_candle      name="Magenta&#xA;Candle"         icon="magenta_candle" tags="beewax beeswax"/>
        <pink_candle         name="Pink&#xA;Candle"            icon="pink_candle" tags="beewax beeswax"/>
        <brown_candle        name="Brown&#xA;Candle"           icon="brown_candle" tags="beewax beeswax"/>
        <light_gray_candle   name="Light Gray&#xA;Candle"      icon="light_gray_candle" tags="beewax beeswax"/>
        <gray_candle         name="Gray&#xA;Candle"            icon="gray_candle" tags="beewax beeswax"/>
        <black_candle        name="Black&#xA;Candle"           icon="black_candle" tags="beewax beeswax"/>
    </candles>
    <cobblestone>
        <cobblestone name="Cobble" icon="cobblestone"/>
        <cobblestone_wall name="Cobble&#xA;Wall" icon="cobblestone_wall"/>
        <cobblestone_stairs name="Cobble&#xA;Stairs" icon="cobblestone_stairs"/>
        <cobblestone_slab name="Cobble&#xA;Slab" icon="cobblestone_slab"/>
        <mossy_cobblestone name="Mossy&#xA;Cobble" icon="mossy_cobblestone"/>
        <mossy_cobblestone_wall name="Mossy&#xA;Cobble&#xA;Wall" icon="mossy_cobblestone_wall"/>
        <mossy_cobblestone_stairs name="Mossy&#xA;Cobble&#xA;Stairs" icon="mossy_cobblestone_stairs"/>
        <mossy_cobblestone_slab name="Mossy&#xA;Cobble&#xA;Slab" icon="mossy_cobblestone_slab"/>
        <smooth_stone name="Smooth&#xA;Stone" icon="smooth_stone"/>
        <smooth_stone_slab name="Smooth&#xA;Stone Slab" icon="smooth_stone_slab"/>
    </cobblestone>
    <deepslate>
        <deepslate                 name="Deepslate"                        icon="deepslate"/>
        <cobbled_deepslate         name="Cobbled Deepslate"                icon="cobbled_deepslate"/>
        <cobbled_deepslate_stairs  name="Cobbled Deepslate&#xA;Stairs"     icon="cobbled_deepslate_stairs"/>
        <cobbled_deepslate_slab    name="Cobbled Deepslate&#xA;Slab"       icon="cobbled_deepslate_slab"/>
        <cobbled_deepslate_wall    name="Cobbled Deepslate&#xA;Wall"       icon="cobbled_deepslate_wall"/>
        <polished_deepslate        name="Polished Deepslate"               icon="polished_deepslate"/>
        <chiseled_deepslate        name="Chiseled Deepslate"               icon="chiseled_deepslate"/>
        <polished_deepslate_stairs name="Polished Deepslate&#xA;Stairs"    icon="polished_deepslate_stairs"/>
        <polished_deepslate_slab   name="Polished Deepslate&#xA;Slab"      icon="polished_deepslate_slab"/>
        <polished_deepslate_wall   name="Polished Deepslate&#xA;Wall"      icon="polished_deepslate_wall"/>
        <deepslate_tiles           name="Deepslate Tiles"                  icon="deepslate_tiles"/>
        <cracked_deepslate_tiles   name="Cracked Deepslate Tiles"          icon="cracked_deepslate_tiles"/>
        <deepslate_tile_stairs     name="Deepslate Tile Stairs"            icon="deepslate_tile_stairs"/>
        <deepslate_tile_slab       name="Deepslate Tile Slab"              icon="deepslate_tile_slab"/>
        <deepslate_tile_wall       name="Deepslate Tile Wall"              icon="deepslate_tile_wall"/>
        <deepslate_bricks          name="Deepslate Bricks"                 icon="deepslate_bricks"/>
        <cracked_deepslate_bricks  name="Cracked Deepslate Bricks"         icon="cracked_deepslate_bricks"/>
        <deepslate_brick_stairs    name="Deepslate Brick Stairs"           icon="deepslate_brick_stairs"/>
        <deepslate_brick_slab      name="Deepslate Brick Slab"             icon="deepslate_brick_slab"/>
        <deepslate_brick_wall      name="Deepslate Brick Wall"             icon="deepslate_brick_wall"/>
    </deepslate>
    <concrete>
        <white_concrete name="White Concrete" icon="white_concrete"/>
        <red_concrete name="Red Concrete" icon="red_concrete"/>
        <orange_concrete name="Orange Concrete" icon="orange_concrete"/>
        <yellow_concrete name="Yellow Concrete" icon="yellow_concrete"/>
        <lime_concrete name="Lime Concrete" icon="lime_concrete"/>
        <green_concrete name="Green Concrete" icon="green_concrete"/>
        <cyan_concrete name="Cyan Concrete" icon="cyan_concrete"/>
        <light_blue_concrete name="Light Blue Concrete" icon="light_blue_concrete"/>
        <blue_concrete name="Blue Concrete" icon="blue_concrete"/>
        <purple_concrete name="Purple Concrete" icon="purple_concrete"/>
        <magenta_concrete name="Magenta Concrete" icon="magenta_concrete"/>
        <pink_concrete name="Pink Concrete" icon="pink_concrete"/>
        <brown_concrete name="Brown Concrete" icon="brown_concrete"/>
        <light_gray_concrete name="Light Gray Concrete" icon="light_gray_concrete"/>
        <gray_concrete name="Gray Concrete" icon="gray_concrete"/>
        <black_concrete name="Black Concrete" icon="black_concrete"/>
        <white_concrete_powder name="White Concrete Powder" icon="white_concrete_powder"/>
        <red_concrete_powder name="Red Concrete Powder" icon="red_concrete_powder"/>
        <orange_concrete_powder name="Orange Concrete Powder" icon="orange_concrete_powder"/>
        <yellow_concrete_powder name="Yellow Concrete Powder" icon="yellow_concrete_powder"/>
        <lime_concrete_powder name="Lime Concrete Powder" icon="lime_concrete_powder"/>
        <green_concrete_powder name="Green Concrete Powder" icon="green_concrete_powder"/>
        <cyan_concrete_powder name="Cyan Concrete Powder" icon="cyan_concrete_powder"/>
        <light_blue_concrete_powder name="Light Blue Concrete Powder" icon="light_blue_concrete_powder"/>
        <blue_concrete_powder name="Blue Concrete Powder" icon="blue_concrete_powder"/>
        <purple_concrete_powder name="Purple Concrete Powder" icon="purple_concrete_powder"/>
        <magenta_concrete_powder name="Magenta Concrete Powder" icon="magenta_concrete_powder"/>
        <pink_concrete_powder name="Pink Concrete Powder" icon="pink_concrete_powder"/>
        <brown_concrete_powder name="Brown Concrete Powder" icon="brown_concrete_powder"/>
        <light_gray_concrete_powder name="Light Gray Concrete Powder" icon="light_gray_concrete_powder"/>
        <gray_concrete_powder name="Gray Concrete Powder" icon="gray_concrete_powder"/>
        <black_concrete_powder name="Black Concrete Powder" icon="black_concrete_powder"/>
    </concrete>
    <crops>
        <wheat_seeds name="Wheat&#xA;Seeds" icon="wheat"/>
        <carrot name="Carrot" icon="carrots"/>
        <beetroot_seeds name="Beetroot&#xA;Seeds" icon="beetroots"/>
        <potato name="Potato" icon="potatoes"/>
        <torchflower_seeds name="Torchflower Seeds" icon="torchflower_seeds"/>
        <pitcher_pod name="Pitcher Pod" icon="pitcher_pod"/>
        <pumpkin_seeds name="Pumpkin&#xA;Seeds" icon="pumpkin_stem"/>
        <melon_seeds name="Melon&#xA;Seeds" icon="melon_stem"/>
    </crops>
    <diorite>
        <diorite name="Diorite" icon="diorite"/>
        <diorite_stairs name="Diorite&#xA;Stairs" icon="diorite_stairs"/>
        <diorite_slab name="Diorite&#xA;Slab" icon="diorite_slab"/>
        <diorite_wall name="Diorite&#xA;Wall" icon="diorite_wall"/>
        <polished_diorite name="Polished&#xA;Diorite" icon="polished_diorite"/>
        <polished_diorite_stairs name="Polished&#xA;Diorite&#xA;Stairs" icon="polished_diorite_stairs"/>
        <polished_diorite_slab name="Polished&#xA;Diorite&#xA;Slab" icon="polished_diorite_slab"/>
    </diorite>
    <dirt>
        <dirt name="Dirt" icon="dirt"/>
        <coarse_dirt name="Coarse Dirt" icon="coarse_dirt"/>
        <rooted_dirt name="Rooted Dirt" icon="rooted_dirt"/>
        <gravel name="Gravel" icon="gravel"/>
        <suspicious_gravel name="Suspicious&#xA;Gravel" icon="suspicious_gravel"/>
    </dirt>
    <doors>
        <oak_door name="Oak Door" icon="oak_door" double_height="true"/>
        <spruce_door name="Spruce Door" icon="spruce_door" double_height="true"/>
        <birch_door name="Birch Door" icon="birch_door" double_height="true"/>
        <jungle_door name="Jungle Door" icon="jungle_door" double_height="true"/>
        <acacia_door name="Acacia Door" icon="acacia_door" double_height="true"/>
        <dark_oak_door name="Dark Oak Door" icon="dark_oak_door" double_height="true"/>
        <crimson_door name="Crimson Door" icon="crimson_door" double_height="true"/>
        <warped_door name="Warped Door" icon="warped_door" double_height="true"/>
        <mangrove_door name="Mangrove Door" icon="mangrove_door" double_height="true"/>
        <cherry_door name="Cherry Door" icon="cherry_door" double_height="true"/>
        <bamboo_door name="Bamboo Door" icon="bamboo_door" double_height="true"/>
    </doors>
    <end_misc>
        <end_stone name="End Stone" icon="end_stone"/>
        <dragon_egg name="Dragon Egg" icon="dragon_egg_block" tags="ender"/>
        <dragon_head name="Dragon&#xA;Head" icon="dragon_head" tags="ender endcity"/>
        <chorus_flower name="Chorus Flower" icon="chorus_flower" tags="end"/>
    </end_misc>
    <end_blocks>
        <end_stone_bricks name="End Stone Bricks" icon="end_stone_bricks" tags="endcity"/>
        <end_stone_brick_stairs name="End Stone Brick Stairs" icon="end_stone_brick_stairs" tags="endcity"/>
        <end_stone_brick_slab name="End Stone Brick Slab" icon="end_stone_brick_slab" tags="endcity"/>
        <end_stone_brick_wall name="End Stone Brick Wall" icon="end_stone_brick_wall" tags="endcity"/>
        <purpur_block name="Purpur Block" icon="purpur_block" tags="endcity"/>
        <purpur_stairs name="Purpur Stairs" icon="purpur_stairs" tags="endcity"/>
        <purpur_slab name="Purpur Slab" icon="purpur_slab" tags="endcity"/>
        <purpur_pillar name="Purpur Pillar" icon="purpur_pillar" tags="endcity"/>
    </end_blocks>
    <flowers>
        <poppy name="Poppy" icon="poppy" tags="flowers"/>
        <dandelion name="Dandelion" icon="dandelion" tags="flowers"/>
        <allium name="Allium" icon="allium" tags="flowers"/>
        <blue_orchid name="Blue Orchid" icon="blue_orchid" tags="flowers"/>
        <cornflower name="Cornflower" icon="cornflower" tags="flowers"/>
        <oxeye_daisy name="Oxeye Daisy" icon="oxeye_daisy" tags="flowers"/>
        <lily_of_the_valley name="Lily of the Valley" icon="lily_of_the_valley" tags="flowers"/>
        <azure_bluet name="Azure Bluet" icon="azure_bluet" tags="flowers"/>
        <red_tulip name="Red Tulip" icon="red_tulip" tags="flowers"/>
        <orange_tulip name="Orange Tulip" icon="orange_tulip" tags="flowers"/>
        <pink_tulip name="Pink Tulip" icon="pink_tulip" tags="flowers"/>
        <white_tulip name="White Tulip" icon="white_tulip" tags="flowers"/>
    </flowers>
    <foliage>
        <oak_sapling name="Oak&#xA;Sapling" icon="oak_sapling"/>
        <oak_leaves name="Oak&#xA;Leaves" icon="oak_leaves"/>
        <spruce_sapling name="Spruce&#xA;Sapling" icon="spruce_sapling"/>
        <spruce_leaves name="Spruce&#xA;Leaves" icon="spruce_leaves"/>
        <birch_sapling name="Birch&#xA;Sapling" icon="birch_sapling"/>
        <birch_leaves name="Birch&#xA;Leaves" icon="birch_leaves"/>
        <jungle_sapling name="Jungle&#xA;Sapling" icon="jungle_sapling"/>
        <jungle_leaves name="Jungle&#xA;Leaves" icon="jungle_leaves"/>
        <acacia_sapling name="Acacia&#xA;Sapling" icon="acacia_sapling"/>
        <acacia_leaves name="Acacia&#xA;Leaves" icon="acacia_leaves"/>
        <dark_oak_sapling name="Dark Oak&#xA;Sapling" icon="dark_oak_sapling"/>
        <dark_oak_leaves name="Dark Oak&#xA;Leaves" icon="dark_oak_leaves"/>
        <crimson_fungus name="Crimson&#xA;Fungus" icon="crimson_fungus" tags="mushrooms"/>
        <nether_wart_block name="Nether Wart&#xA;Block" icon="nether_wart_block" tags="leaves"/>
        <warped_fungus name="Warped Fungus" icon="warped_fungus" tags="mushrooms"/>
        <warped_wart_block name="Warped Wart&#xA;Block" icon="warped_wart_block" tags="leaves"/>
        <cherry_sapling name="Cherry&#xA;Sapling" icon="cherry_sapling"/>
        <cherry_leaves name="Cherry&#xA;Leaves" icon="cherry_leaves"/>
        <mangrove_propagule name="Mangrove&#xA;Propagule" icon="mangrove_propagule" tags="sapling"/>
        <mangrove_leaves name="Mangrove&#xA;Leaves" icon="mangrove_leaves"/>
        <bamboo name="Bamboo" icon="bamboo_sapling" tags="jungle"/>
        <bamboo_block name="Block of&#xA;Bamboo" icon="bamboo_block"/>
    </foliage>
    <food>
        <cocoa_beans name="Cocoa&#xA;Beans" icon="cocoa_beans" tags="jungle"/>
        <mushroom_stem name="Mushroom Stem" icon="mushroom_stem"/>
        <red_mushroom_block name="Red Mushroom Block" icon="red_mushroom_block"/>
        <brown_mushroom_block name="Brown Mushroom Block" icon="brown_mushroom_block"/>
        <red_mushroom name="Red Mushroom" icon="red_mushroom"/>
        <brown_mushroom name="Brown Mushroom" icon="brown_mushroom"/>
        <cake name="Cake" icon="cake"/>
        <hay_block name="Hay Bale" icon="hay_block"/>
        <melon name="Melon" icon="melon"/>
        <pumpkin name="Pumpkin" icon="pumpkin"/>
        <carved_pumpkin name="Carved Pumpkin" icon="carved_pumpkin"/>
        <jack_o_lantern name="Jack O' Lantern" icon="jack_o_lantern" light_level="0.8"/>
    </food>
    <glass>
        <glass name="Glass" icon="glass"/>
        <white_stained_glass name="White&#xA;Stained&#xA;Glass" icon="white_stained_glass"/>
        <red_stained_glass name="Red&#xA;Stained&#xA;Glass" icon="red_stained_glass"/>
        <orange_stained_glass name="Orange&#xA;Stained&#xA;Glass" icon="orange_stained_glass"/>
        <yellow_stained_glass name="Yellow&#xA;Stained&#xA;Glass" icon="yellow_stained_glass"/>
        <lime_stained_glass name="Lime&#xA;Stained&#xA;Glass" icon="lime_stained_glass"/>
        <green_stained_glass name="Green&#xA;Stained&#xA;Glass" icon="green_stained_glass"/>
        <cyan_stained_glass name="Cyan&#xA;Stained&#xA;Glass" icon="cyan_stained_glass"/>
        <light_blue_stained_glass name="Light Blue&#xA;Stained&#xA;Glass" icon="light_blue_stained_glass"/>
        <blue_stained_glass name="Blue&#xA;Stained&#xA;Glass" icon="blue_stained_glass"/>
        <purple_stained_glass name="Purple&#xA;Stained&#xA;Glass" icon="purple_stained_glass"/>
        <magenta_stained_glass name="Magenta&#xA;Stained&#xA;Glass" icon="magenta_stained_glass"/>
        <pink_stained_glass name="Pink&#xA;Stained&#xA;Glass" icon="pink_stained_glass"/>
        <brown_stained_glass name="Brown&#xA;Stained&#xA;Glass" icon="brown_stained_glass"/>
        <light_gray_stained_glass name="Light Gray&#xA;Stained&#xA;Glass" icon="light_gray_stained_glass"/>
        <gray_stained_glass name="Gray&#xA;Stained&#xA;Glass" icon="gray_stained_glass"/>
        <black_stained_glass name="Black&#xA;Stained&#xA;Glass" icon="black_stained_glass"/>
        <glass_pane name="Glass Pane" icon="glass_pane"/>
        <white_stained_glass_pane name="White&#xA;Stained&#xA;Glass&#160;Pane" icon="white_stained_glass_pane"/>
        <red_stained_glass_pane name="Red&#xA;Stained&#xA;Glass&#160;Pane" icon="red_stained_glass_pane"/>
        <orange_stained_glass_pane name="Orange&#xA;Stained&#xA;Glass&#160;Pane" icon="orange_stained_glass_pane"/>
        <yellow_stained_glass_pane name="Yellow&#xA;Stained&#xA;Glass&#160;Pane" icon="yellow_stained_glass_pane"/>
        <lime_stained_glass_pane name="Lime&#xA;Stained&#xA;Glass&#160;Pane" icon="lime_stained_glass_pane"/>
        <green_stained_glass_pane name="Green&#xA;Stained&#xA;Glass&#160;Pane" icon="green_stained_glass_pane"/>
        <cyan_stained_glass_pane name="Cyan&#xA;Stained&#xA;Glass&#160;Pane" icon="cyan_stained_glass_pane"/>
        <light_blue_stained_glass_pane name="Light Blue&#xA;Stained&#xA;Glass&#160;Pane" icon="light_blue_stained_glass_pane"/>
        <blue_stained_glass_pane name="Blue&#xA;Stained&#xA;Glass&#160;Pane" icon="blue_stained_glass_pane"/>
        <purple_stained_glass_pane name="Purple&#xA;Stained&#xA;Glass&#160;Pane" icon="purple_stained_glass_pane"/>
        <magenta_stained_glass_pane name="Magenta&#xA;Stained&#xA;Glass&#160; Pane" icon="magenta_stained_glass_pane"/>
        <pink_stained_glass_pane name="Pink&#xA;Stained&#xA;Glass&#160;Pane" icon="pink_stained_glass_pane"/>
        <brown_stained_glass_pane name="Brown&#xA;Stained&#xA;Glass&#160;Pane" icon="brown_stained_glass_pane"/>
        <light_gray_stained_glass_pane name="Light Gray&#xA;Stained&#xA;Glass&#160;Pane" icon="light_gray_stained_glass_pane"/>
        <gray_stained_glass_pane name="Gray&#xA;Stained&#xA;Glass&#160;Pane" icon="gray_stained_glass_pane"/>
        <black_stained_glass_pane name="Black&#xA;Stained&#xA;Glass&#160;Pane" icon="black_stained_glass_pane"/>
        <tinted_glass name="Tinted Glass" icon="tinted_glass"/>
    </glass>
    <glazed_terracotta>
        <white_glazed_terracotta name="White&#xA;Glazed&#xA;Terracotta" icon="white_glazed_terracotta"/>
        <red_glazed_terracotta name="Red&#xA;Glazed&#xA;Terracotta" icon="red_glazed_terracotta"/>
        <orange_glazed_terracotta name="Orange&#xA;Glazed&#xA;Terracotta" icon="orange_glazed_terracotta"/>
        <yellow_glazed_terracotta name="Yellow&#xA;Glazed&#xA;Terracotta" icon="yellow_glazed_terracotta"/>
        <lime_glazed_terracotta name="Lime&#xA;Glazed&#xA;Terracotta" icon="lime_glazed_terracotta"/>
        <green_glazed_terracotta name="Green&#xA;Glazed&#xA;Terracotta" icon="green_glazed_terracotta"/>
        <cyan_glazed_terracotta name="Cyan&#xA;Glazed&#xA;Terracotta" icon="cyan_glazed_terracotta"/>
        <light_blue_glazed_terracotta name="Light Blue&#xA;Glazed&#xA;Terracotta" icon="light_blue_glazed_terracotta"/>
        <blue_glazed_terracotta name="Blue&#xA;Glazed&#xA;Terracotta" icon="blue_glazed_terracotta"/>
        <purple_glazed_terracotta name="Purple&#xA;Glazed&#xA;Terracotta" icon="purple_glazed_terracotta"/>
        <magenta_glazed_terracotta name="Magenta&#xA;Glazed&#xA;Terracotta" icon="magenta_glazed_terracotta"/>
        <pink_glazed_terracotta name="Pink&#xA;Glazed&#xA;Terracotta" icon="pink_glazed_terracotta"/>
        <brown_glazed_terracotta name="Brown&#xA;Glazed&#xA;Terracotta" icon="brown_glazed_terracotta"/>
        <light_gray_glazed_terracotta name="Light Gray&#xA;Glazed&#xA;Terracotta" icon="light_gray_glazed_terracotta"/>
        <gray_glazed_terracotta name="Gray&#xA;Glazed&#xA;Terracotta" icon="gray_glazed_terracotta"/>
        <black_glazed_terracotta name="Black&#xA;Glazed&#xA;Terracotta" icon="black_glazed_terracotta"/>
    </glazed_terracotta>
    <granite>
        <empty/>
        <granite name="Granite" icon="granite"/>
        <granite_stairs name="Granite&#xA;Stairs" icon="granite_stairs"/>
        <granite_slab name="Granite&#xA;Slab" icon="granite_slab"/>
        <granite_wall name="Granite&#xA;Wall" icon="granite_wall"/>
        <polished_granite name="Polished&#xA;Granite" icon="polished_granite"/>
        <polished_granite_stairs name="Polished&#xA;Granite&#xA;Stairs" icon="polished_granite_stairs"/>
        <polished_granite_slab name="Polished&#xA;Granite&#xA;Slab" icon="polished_granite_slab"/>
    </granite>
    <grass>
        <grass_block name="Grass Block" icon="grass_block"/>
        <podzol name="Podzol" icon="podzol" tags="grass"/>
        <mycelium name="Mycelium" icon="mycelium" tags="grass"/>
        <clay name="Clay" icon="clay"/>
    </grass>
    <wither_rose>
        <wither_rose name="Wither Rose" icon="wither_rose" tags="flowers"/>
    </wither_rose>
    <heads>
        <creeper_head name="Creeper&#xA;Head" icon="creeper_head"/>
        <skeleton_skull name="Skeleton&#xA;Skull" icon="skeleton_skull"/>
        <wither_skeleton_skull name="Wither&#xA;Skull" icon="wither_skeleton_skull"/>
        <zombie_head name="Zombie&#xA;Head" icon="zombie_head"/>
        <piglin_head name="Piglin&#xA;Head" icon="piglin_head"/>
    </heads>
    <lights>
        <torch name="Torch" icon="torch" light_level="0.5"/>
        <soul_torch name="Soul Torch" icon="soul_torch" light_level="0.5"/>
        <empty/>
        <lantern name="Lantern" icon="lantern" light_level="0.7"/>
        <soul_lantern name="Soul Lantern" icon="soul_lantern" light_level="0.7"/>
        <chain name="Chain" icon="chain"/>
        <campfire name="Campfire" icon="campfire" light_level="0.7"/>
        <soul_campfire name="Soul Campfire" icon="soul_campfire" light_level="0.7"/>
    </lights>
    <random_stuff>
        <water_bucket name="Water" icon="water"/>
        <jukebox name="Jukebox" icon="jukebox"/>
        <note_block name="Note Block" icon="note_block"/>
    </random_stuff>
    <materials>
        <diamond_block name="Diamond&#xA;Block" icon="diamond_block"/>
        <emerald_block name="Emerald&#xA;Block" icon="emerald_block"/>
        <lapis_block name="Lapis Lazuli&#xA;Block" icon="lapis_block"/>
        <redstone_block name="Redstone&#xA;Block" icon="redstone_block" light_level="0.6"/>
        <gold_block name="Gold&#xA;Block" icon="gold_block"/>
        <iron_block name="Iron&#xA;Block" icon="iron_block"/>
        <lightning_rod name="Lightning&#xA;Rod" icon="lightning_rod_block" tags="copper"/>
        <coal_block name="Coal&#xA;Block" icon="coal_block"/>
        <diamond_ore name="Diamond&#xA;Ore" icon="diamond_ore"/>
        <emerald_ore name="Emerald&#xA;Ore" icon="emerald_ore"/>
        <lapis_ore name="Lapis Lazuli&#xA;Ore" icon="lapis_ore"/>
        <redstone_ore name="Redstone&#xA;Ore" icon="redstone_ore" light_level="0.3"/>
        <gold_ore name="Gold&#xA;Ore" icon="gold_ore"/>
        <iron_ore name="Iron&#xA;Ore" icon="iron_ore"/>
        <copper_ore name="Copper&#xA;Ore" icon="copper_ore"/>
        <coal_ore name="Coal&#xA;Ore" icon="coal_ore"/>
        <deepslate_diamond_ore name="Deepslate&#xA;Diamond&#xA;Ore" icon="deepslate_diamond_ore"/>
        <deepslate_emerald_ore name="Deepslate&#xA;Emerald&#xA;Ore" icon="deepslate_emerald_ore"/>
        <deepslate_lapis_ore name="Deepslate&#xA;Lapis Lazuli&#xA;Ore" icon="deepslate_lapis_ore"/>
        <deepslate_redstone_ore name="Deepslate&#xA;Redstone&#xA;Ore" icon="deepslate_redstone_ore" light_level="0.3"/>
        <deepslate_gold_ore name="Deepslate&#xA;Gold&#xA;Ore" icon="deepslate_gold_ore"/>
        <deepslate_iron_ore name="Deepslate&#xA;Iron&#xA;Ore" icon="deepslate_iron_ore"/>
        <deepslate_copper_ore name="Deepslate&#xA;Copper&#xA;Ore" icon="deepslate_copper_ore"/>
        <deepslate_coal_ore name="Deepslate&#xA;Coal&#xA;Ore" icon="deepslate_coal_ore"/>
    </materials>
    <minerals>
        <raw_gold_block name="Raw Gold Block" icon="raw_gold_block"/>
        <raw_iron_block name="Raw Iron Block" icon="raw_iron_block"/>
        <raw_copper_block name="Raw Copper Block" icon="raw_copper_block"/>
        <calcite name="Calcite" icon="calcite" tags="geode"/>
        <amethyst_block       name="Block of Amethyst"        icon="amethyst_block" light_level="0.4" tags="geode"/>
        <amethyst_cluster     name="Amethyst Cluster"         icon="amethyst_cluster" light_level="0.4" tags="geode"/>
        <large_amethyst_bud   name="Large Amethyst&#xA;Bud"   icon="large_amethyst_bud" light_level="0.4" tags="geode"/>
        <medium_amethyst_bud  name="Medium Amethyst&#xA;Bud"  icon="medium_amethyst_bud" light_level="0.3" tags="geode"/>
        <small_amethyst_bud   name="Small Amethyst&#xA;Bud"   icon="small_amethyst_bud" light_level="0.2" tags="geode"/>
    </minerals>
    <dripstone>
        <dripstone_block name="Dripstone Block" icon="dripstone_block"/>
        <pointed_dripstone name="Pointed Dripstone" icon="pointed_dripstone"/>
    </dripstone>
    <tuff>
        <chiseled_tuff_bricks name="Chiseled&#xA;Tuff&#160;Bricks" icon="chiseled_tuff_bricks"/>
        <chiseled_tuff name="Chiseled&#xA;Tuff" icon="chiseled_tuff"/>
        <tuff name="Tuff" icon="tuff"/>
        <tuff_wall name="Tuff Wall" icon="tuff_wall"/>
        <tuff_stairs name="Tuff Stairs" icon="tuff_stairs"/>
        <tuff_slab name="Tuff Slab" icon="tuff_slab"/>
        <polished_tuff name="Polished&#xA;Tuff" icon="polished_tuff"/>
        <polished_tuff_wall name="Polished&#xA;Tuff&#160;Wall" icon="polished_tuff_wall"/>
        <polished_tuff_stairs name="Polished&#xA;Tuff&#160;Stairs" icon="polished_tuff_stairs"/>
        <polished_tuff_slab name="Polished&#xA;Tuff&#160;Slab" icon="polished_tuff_slab"/>
        <tuff_bricks name="Tuff&#xA;Bricks" icon="tuff_bricks"/>
        <tuff_brick_wall name="Tuff Brick&#160;Wall" icon="tuff_brick_wall"/>
        <tuff_brick_stairs name="Tuff Brick&#160;Stairs" icon="tuff_brick_stairs"/>
        <tuff_brick_slab name="Tuff Brick&#160;Slab" icon="tuff_brick_slab"/>
    </tuff>
    <copper>
        <waxed_copper_block name="Waxed&#xA;Block of Copper" icon="copper_block"/>
        <waxed_chiseled_copper name="Waxed&#xA;Chiseled&#xA;Copper" icon="chiseled_copper"/>
        <waxed_copper_bulb name="Waxed&#xA;Copper&#xA;Bulb" icon="copper_bulb"/>
        <waxed_copper_grate name="Waxed&#xA;Copper&#xA;Grate" icon="copper_grate"/>
        <waxed_cut_copper name="Waxed&#xA;Cut&#160;Copper&#xA;Block" icon="cut_copper"/>
        <waxed_cut_copper_stairs name="Waxed&#xA;Cut&#160;Copper&#xA;Stair" icon="cut_copper_stairs"/>
        <waxed_cut_copper_slab name="Waxed&#xA;Cut&#160;Copper&#xA;Slab" icon="cut_copper_slab"/>
        <waxed_copper_trapdoor name="Waxed&#xA;Copper&#xA;Trapdoor" icon="copper_trapdoor"/>
        <waxed_copper_door name="Waxed&#xA;Copper&#xA;Door" icon="copper_door" double_height="true"/>
        
        <waxed_exposed_copper name="Waxed&#xA;Exposed&#xA;Copper" icon="exposed_copper"/>
        <waxed_exposed_chiseled_copper name="Waxed&#xA;Exposed&#xA;Chiseled" icon="exposed_chiseled_copper"/>
        <waxed_exposed_copper_bulb name="Waxed&#xA;Exposed&#xA;Bulb" icon="exposed_copper_bulb"/>
        <waxed_exposed_copper_grate name="Waxed&#xA;Exposed&#xA;Grate" icon="exposed_copper_grate"/>
        <waxed_exposed_cut_copper name="Waxed&#xA;Exposed Cut&#160;Copper" icon="exposed_cut"/>
        <waxed_exposed_cut_copper_stairs name="Waxed&#xA;Exposed&#xA;Copper&#160;Stair" icon="exposed_stairs" tags="cut"/>
        <waxed_exposed_cut_copper_slab name="Waxed&#xA;Exposed&#xA;Copper&#160;Slab" icon="exposed_slab" tags="cut"/>
        <waxed_exposed_copper_trapdoor name="Waxed&#xA;Exposed&#xA;Trapdoor" icon="exposed_copper_trapdoor"/>
        <waxed_exposed_copper_door name="Waxed&#xA;Exposed&#xA;Door" icon="exposed_copper_door" double_height="true"/>
        
        <waxed_weathered_copper name="Waxed&#xA;Weathered&#xA;Copper" icon="weathered_copper"/>
        <waxed_weathered_chiseled_copper name="Waxed&#xA;Weathered&#xA;Chiseled" icon="weathered_chiseled_copper"/>
        <waxed_weathered_copper_bulb name="Waxed&#xA;Weathered&#xA;Bulb" icon="weathered_copper_bulb"/>
        <waxed_weathered_copper_grate name="Waxed&#xA;Weathered&#xA;Grate" icon="weathered_copper_grate"/>
        <waxed_weathered_cut_copper name="Waxed&#xA;Weathered Cut&#160;Copper" icon="weathered_cut"/>
        <waxed_weathered_cut_copper_stairs name="Waxed&#xA;Weathered&#xA;Copper&#160;Stair" icon="weathered_stairs" tags="cut"/>
        <waxed_weathered_cut_copper_slab name="Waxed&#xA;Weathered&#xA;Copper&#160;Slab" icon="weathered_slab" tags="cut"/>
        <waxed_weathered_copper_trapdoor name="Waxed&#xA;Weathered&#xA;Trapdoor" icon="weathered_copper_trapdoor"/>
        <waxed_weathered_copper_door name="Waxed&#xA;Weathered&#xA;Door" icon="weathered_copper_door" double_height="true"/>
        
        <waxed_oxidized_copper name="Waxed&#xA;Oxidized&#xA;Copper" icon="oxidized_copper"/>
        <waxed_oxidized_chiseled_copper name="Waxed&#xA;Oxidized&#xA;Chiseled" icon="oxidized_chiseled_copper"/>
        <waxed_oxidized_copper_bulb name="Waxed&#xA;Oxidized&#xA;Bulb" icon="oxidized_copper_bulb"/>
        <waxed_oxidized_copper_grate name="Waxed&#xA;Oxidized&#xA;Grate" icon="oxidized_copper_grate"/>
        <waxed_oxidized_cut_copper name="Waxed&#xA;Oxidized Cut&#160;Copper" icon="oxidized_cut"/>
        <waxed_oxidized_cut_copper_stairs name="Waxed&#xA;Oxidized&#xA;Copper&#160;Stair" icon="oxidized_stairs" tags="cut"/>
        <waxed_oxidized_cut_copper_slab name="Waxed&#xA;Oxidized&#xA;Copper&#160;Slab" icon="oxidized_slab" tags="cut"/>
        <waxed_oxidized_copper_trapdoor name="Waxed&#xA;Oxidized&#xA;Trapdoor" icon="oxidized_copper_trapdoor"/>
        <waxed_oxidized_copper_door name="Waxed&#xA;Oxidized&#xA;Door" icon="oxidized_copper_door" double_height="true"/>
    </copper>
    <heavy_core>
        <heavy_core name="Heavy Core" icon="heavy_core_block"/>
    </heavy_core>
    <nether_basic>
        <netherrack name="Netherrack" icon="netherrack_block"/>
        <crimson_nylium name="Crimson Nylium" icon="crimson_nylium" tags="netherrack grass silktouch"/>
        <warped_nylium name="Warped Nylium" icon="warped_nylium" tags="netherrack grass silktouch"/>
        <soul_sand name="Soul Sand" icon="soul_sand"/>
        <soul_soil name="Soul Soil" icon="soul_soil"/>
        <bone_block name="Bone Block" icon="bone_block"/>
        <basalt name="Basalt" icon="basalt"/>
        <polished_basalt name="Polished Basalt" icon="polished_basalt"/>
        <smooth_basalt name="Smooth Basalt" icon="smooth_basalt" tags="geode"/>
    </nether_basic>
    <nether_brick>
        <nether_bricks name="Nether&#xA;Bricks" icon="nether_bricks"/>
        <nether_brick_stairs name="Nether&#xA;Brick&#xA;Stairs" icon="nether_brick_stairs"/>
        <nether_brick_slab name="Nether&#xA;Brick&#xA;Slab" icon="nether_brick_slab"/>
        <nether_brick_fence name="Nether&#xA;Brick&#xA;Fence" icon="nether_brick_fence"/>
        <cracked_nether_bricks name="Cracked&#xA;Nether&#xA;Bricks" icon="cracked_nether_bricks"/>
        <chiseled_nether_bricks name="Chiseled&#xA;Nether&#xA;Bricks" icon="chiseled_nether_bricks"/>
        <nether_wart name="Nether Wart" icon="nether_wart_planted"/>
        <nether_brick_wall name="Nether&#160;Brick&#xA;Wall" icon="nether_brick_wall"/>
        <red_nether_bricks name="Red&#xA;Nether&#xA;Bricks" icon="red_nether_bricks"/>
        <red_nether_brick_stairs name="Red&#xA;Nether&#160;Brick Stairs" icon="red_nether_brick_stairs"/>
        <red_nether_brick_slab name="Red&#xA;Nether&#160;Brick Slab" icon="red_nether_brick_slab"/>
        <red_nether_brick_wall name="Red&#xA;Nether&#160;Brick Wall" icon="red_nether_brick_wall"/>
    </nether_brick>
    <small_foliage>
        <warped_roots name="Warped&#xA;Roots" icon="warped_roots"/>
        <nether_sprouts name="Nether&#xA;Sprouts" icon="nether_sprouts"/>
        <crimson_roots name="Crimson&#xA;Roots" icon="crimson_roots"/>
        <hanging_roots name="Hanging&#xA;Roots" icon="hanging_roots"/>
    </small_foliage>
    <nether_special>
        <netherite_block name="Block of Netherite" icon="netherite_block" tags="debris"/>
        <ancient_debris name="Ancient Debris" icon="ancient_debris" tags="netherite"/>
        <lodestone name="Lodestone" icon="lodestone" tags="netherite"/>
        <nether_gold_ore name="Nether&#xA;Gold Ore" icon="nether_gold_ore" tags="silktouch"/>
        <nether_quartz_ore name="Nether&#xA;Quartz Ore" icon="nether_quartz_ore" tags="silktouch"/>
        <glowstone name="Glowstone" icon="glowstone" light_level="0.9"/>
        <obsidian name="Obsidian" icon="obsidian"/>
        <crying_obsidian name="Crying Obsidian" icon="crying_obsidian" light_level="0.5"/>
        <respawn_anchor name="Respawn Anchor" icon="respawn_anchor" light_level="0.5" tags="cryingobsidian"/>
        <lava_bucket name="Lava" icon="lava" light_level="1"/>
        <magma_block name="Magma Block" icon="magma_block" light_level="0.7"/>
        <shroomlight name="Shroom Light" icon="shroomlight" light_level="0.75"/>
    </nether_special>
    <ocean_monument>
        <prismarine name="Prismarine" icon="prismarine"/>
        <prismarine_stairs name="Prismarine Stairs" icon="prismarine_stairs"/>
        <prismarine_slab name="Prismarine Slab" icon="prismarine_slab"/>
        <prismarine_wall name="Prismarine Wall" icon="prismarine_wall"/>
        <prismarine_bricks name="Prismarine Bricks" icon="prismarine_bricks"/>
        <prismarine_brick_stairs name="Prismarine Brick Stairs" icon="prismarine_brick_stairs"/>
        <prismarine_brick_slab name="Prismarine Brick Slab" icon="prismarine_brick_slab"/>
        <sea_lantern name="Sea Lantern" icon="sea_lantern" light_level="0.75"/>
        <dark_prismarine name="Dark Prismarine" icon="dark_prismarine"/>
        <dark_prismarine_stairs name="Dark Prismarine Stairs" icon="dark_prismarine_stairs"/>
        <dark_prismarine_slab name="Dark Prismarine Slab" icon="dark_prismarine_slab"/>
        <conduit name="Conduit" icon="conduit" light_level="0.5"/>
    </ocean_monument>
    <sponge>
        <sponge name="Sponge" icon="sponge"/>
        <wet_sponge name="Wet Sponge" icon="wet_sponge"/>
    </sponge>
    <ocean_misc>
        <dried_kelp_block name="Dried Kelp Block" icon="dried_kelp_block"/>
        <turtle_egg name="Turtle Egg" icon="turtle_egg" tags="silktouch"/>
        <sea_pickle name="Sea Pickle" icon="sea_pickle"/>
        <seagrass name="Seagrass" icon="seagrass"/>
    </ocean_misc>
    <ocean_kelp>
        <kelp name="Kelp" icon="kelp" double_height="true"/>
    </ocean_kelp>
    <coral>
        <fire_coral_block name="Fire&#160;Coral Block" icon="fire_coral_block" tags="silktouch"/>
        <horn_coral_block name="Horn&#160;Coral Block" icon="horn_coral_block" tags="silktouch"/>
        <tube_coral_block name="Tube&#160;Coral Block" icon="tube_coral_block" tags="silktouch"/>
        <bubble_coral_block name="Bubble&#160;Coral Block" icon="bubble_coral_block" tags="silktouch"/>
        <brain_coral_block name="Brain&#160;Coral Block" icon="brain_coral_block" tags="silktouch"/>
        <fire_coral name="Fire&#160;Coral" icon="fire_coral" tags="silktouch"/>
        <horn_coral name="Horn&#160;Coral" icon="horn_coral" tags="silktouch"/>
        <tube_coral name="Tube&#160;Coral" icon="tube_coral" tags="silktouch"/>
        <bubble_coral name="Bubble&#160;Coral" icon="bubble_coral" tags="silktouch"/>
        <brain_coral name="Brain&#160;Coral" icon="brain_coral" tags="silktouch"/>
        <fire_coral_fan name="Fire&#160;Coral Fan" icon="fire_coral_fan" tags="silktouch"/>
        <horn_coral_fan name="Horn&#160;Coral Fan" icon="horn_coral_fan" tags="silktouch"/>
        <tube_coral_fan name="Tube&#160;Coral Fan" icon="tube_coral_fan" tags="silktouch"/>
        <bubble_coral_fan name="Bubble&#160;Coral Fan" icon="bubble_coral_fan" tags="silktouch"/>
        <brain_coral_fan name="Brain&#160;Coral Fan" icon="brain_coral_fan" tags="silktouch"/>
    </coral>
    <dead_coral>
        <dead_fire_coral_block name="Dead Fire&#160;Coral Block" icon="dead_fire_coral_block"/>
        <dead_horn_coral_block name="Dead Horn&#160;Coral Block" icon="dead_horn_coral_block"/>
        <dead_tube_coral_block name="Dead Tube&#160;Coral Block" icon="dead_tube_coral_block"/>
        <dead_bubble_coral_block name="Dead Bubble&#160;Coral Block" icon="dead_bubble_coral_block"/>
        <dead_brain_coral_block name="Dead Brain&#160;Coral Block" icon="dead_brain_coral_block"/>
        <dead_fire_coral name="Dead Fire&#160;Coral" icon="dead_fire_coral"/>
        <dead_horn_coral name="Dead Horn&#160;Coral" icon="dead_horn_coral"/>
        <dead_tube_coral name="Dead Tube&#160;Coral" icon="dead_tube_coral"/>
        <dead_bubble_coral name="Dead Bubble&#160;Coral" icon="dead_bubble_coral"/>
        <dead_brain_coral name="Dead Brain&#160;Coral" icon="dead_brain_coral"/>
        <dead_fire_coral_fan name="Dead Fire&#160;Coral Fan" icon="dead_fire_coral_fan"/>
        <dead_horn_coral_fan name="Dead Horn&#160;Coral Fan" icon="dead_horn_coral_fan"/>
        <dead_tube_coral_fan name="Dead Tube&#160;Coral Fan" icon="dead_tube_coral_fan"/>
        <dead_bubble_coral_fan name="Dead Bubble&#160;Coral Fan" icon="dead_bubble_coral_fan"/>
        <dead_brain_coral_fan name="Dead Brain&#160;Coral Fan" icon="dead_brain_coral_fan"/>
    </dead_coral>
    <quartz>
        <quartz_block name="Quartz&#xA;Block" icon="quartz_block"/>
        <chiseled_quartz_block name="Chiseled&#xA;Quartz&#xA;Block" icon="chiseled_quartz_block"/>
        <quartz_pillar name="Quartz&#xA;Pillar" icon="quartz_pillar"/>
        <quartz_bricks name="Quartz&#xA;Bricks" icon="quartz_bricks"/>
        <quartz_stairs name="Quartz&#xA;Stairs" icon="quartz_stairs"/>
        <smooth_quartz_stairs name="Smooth&#xA;Quartz&#xA;Stairs" icon="smooth_quartz_stairs"/>
        <smooth_quartz name="Smooth&#xA;Quartz" icon="smooth_quartz"/>
        <quartz_slab name="Quartz&#xA;Slab" icon="quartz_slab"/>
        <smooth_quartz_slab name="Smooth&#xA;Quartz&#xA;Slab" icon="smooth_quartz_slab"/>
    </quartz>
    <rails>
        <rail name="Rail" icon="rail"/>
        <detector_rail name="Detector&#xA;Rail" icon="detector_rail"/>
        <activator_rail name="Activator&#xA;Rail" icon="activator_rail"/>
        <powered_rail name="Powered&#xA;Rail" icon="powered_rail"/>
    </rails>
    <extra_pressure_plates>
        <heavy_weighted_pressure_plate name="Heavy Pressure Plate" icon="heavy_plate"/>
        <light_weighted_pressure_plate name="Light Pressure Plate" icon="light_plate"/>
        <stone_pressure_plate name="Stone Pressure Plate" icon="stone_plate"/>
        <polished_blackstone_pressure_plate name="Blackstone Pressure Plate" icon="blackstone_plate"/>
    </extra_pressure_plates>
    <extra_buttons>
        <stone_button name="Stone&#xA;Button" icon="stone_button"/>
        <polished_blackstone_button name="Blackstone&#xA;Button" icon="blackstone_button"/>
        <lever name="Lever" icon="lever"/>
        <tripwire_hook name="Tripwire&#xA;Hook" icon="tripwire_hook"/>
    </extra_buttons>
    <ladders>
        <ladder name="Ladder" icon="ladder"/>
        <scaffolding name="Scaffolding" icon="scaffolding"/>
    </ladders>
    <redstone_dust>
        <redstone name="Redstone Dust" icon="redstone_dust" light_level="0.5"/>
        <redstone_torch name="Redstone Torch" icon="redstone_torch" light_level="0.5"/>
    </redstone_dust>
    <red_sandstone>
        <red_sand name="Red Sand" icon="red_sand"/>
        <red_sandstone name="Red Sandstone" icon="red_sandstone"/>
        <red_sandstone_wall name="Red Sandstone Wall" icon="red_sandstone_wall"/>
        <cut_red_sandstone name="Cut Red Sandstone" icon="cut_red_sandstone"/>
        <red_sandstone_stairs name="Red Sandstone Stairs" icon="red_sandstone_stairs"/>
        <red_sandstone_slab name="Red Sandstone Slab" icon="red_sandstone_slab"/>
        <chiseled_red_sandstone name="Chiseled Red Sandstone" icon="chiseled_red_sandstone"/>
        <empty/>
        <cut_red_sandstone_slab name="Cut Red Sandstone Slab" icon="cut_red_sandstone_slab"/>
        <smooth_red_sandstone name="Smooth Red Sandstone" icon="smooth_red_sandstone"/>
        <smooth_red_sandstone_stairs name="Smooth Red Sandstone Stairs" icon="smooth_red_sandstone_stairs"/>
        <smooth_red_sandstone_slab name="Smooth Red Sandstone Slab" icon="smooth_red_sandstone_slab"/>
    </red_sandstone>
    <sandstone>
        <sand name="Sand" icon="sand"/>
        <sandstone name="Sandstone" icon="sandstone"/>
        <sandstone_wall name="Sandstone Wall" icon="sandstone_wall"/>
        <cut_sandstone name="Cut Sandstone" icon="cut_sandstone"/>
        <sandstone_stairs name="Sandstone Stairs" icon="sandstone_stairs"/>
        <sandstone_slab name="Sandstone Slab" icon="sandstone_slab"/>
        <chiseled_sandstone name="Chiseled Sandstone" icon="chiseled_sandstone"/>
        <suspicious_sand name="Suspicious&#xA;Sand" icon="suspicious_sand"/>
        <cut_sandstone_slab name="Cut Sandstone Slab" icon="cut_sandstone_slab"/>
        <smooth_sandstone name="Smooth Sandstone" icon="smooth_sandstone"/>
        <smooth_sandstone_stairs name="Smooth Sandstone Stairs" icon="smooth_sandstone_stairs"/>
        <smooth_sandstone_slab name="Smooth Sandstone Slab" icon="smooth_sandstone_slab"/>
    </sandstone>
    <shrubs>
        <empty/>
        <grass name="Grass" icon="short_grass" alternate_ids="minecraft:short_grass"/>
        <fern name="Fern" icon="fern" tags="grass"/>
        <dead_bush name="Dead Bush" icon="dead_bush"/>
        <spore_blossom name="Spore Blossom" icon="spore_blossom" tags="lush"/>
        <sweet_berries name="Sweet Berry Bush" icon="sweet_berry_bush"/>
        <torchflower name="Torchflower" icon="torchflower"/>
        <sniffer_egg name="Sniffer Egg" icon="sniffer_egg"/>
    </shrubs>
    <natural_transparent>
        <string name="String" icon="string"/>
        <cobweb name="Cobweb" icon="cobweb"/>
        <pink_petals name="Pink Petals" icon="pink_petals"/>
    </natural_transparent>
    <shulker_boxes>
        <white_shulker_box name="White&#xA;Shulker&#xA;Box" icon="white_shulker_box"/>
        <red_shulker_box name="Red&#xA;Shulker&#xA;Box" icon="red_shulker_box"/>
        <orange_shulker_box name="Orange&#xA;Shulker&#xA;Box" icon="orange_shulker_box"/>
        <yellow_shulker_box name="Yellow&#xA;Shulker&#xA;Box" icon="yellow_shulker_box"/>
        <lime_shulker_box name="Lime&#xA;Shulker&#xA;Box" icon="lime_shulker_box"/>
        <green_shulker_box name="Green&#xA;Shulker&#xA;Box" icon="green_shulker_box"/>
        <cyan_shulker_box name="Cyan&#xA;Shulker&#xA;Box" icon="cyan_shulker_box"/>
        <light_blue_shulker_box name="Light Blue&#xA;Shulker&#xA;Box" icon="light_blue_shulker_box"/>
        <blue_shulker_box name="Blue&#xA;Shulker&#xA;Box" icon="blue_shulker_box"/>
        <purple_shulker_box name="Purple&#xA;Shulker&#xA;Box" icon="purple_shulker_box"/>
        <magenta_shulker_box name="Magenta&#xA;Shulker&#xA;Box" icon="magenta_shulker_box"/>
        <pink_shulker_box name="Pink&#xA;Shulker&#xA;Box" icon="pink_shulker_box"/>
        <brown_shulker_box name="Brown&#xA;Shulker&#xA;Box" icon="brown_shulker_box"/>
        <light_gray_shulker_box name="Light Gray&#xA;Shulker&#xA;Box" icon="light_gray_shulker_box"/>
        <gray_shulker_box name="Gray&#xA;Shulker&#xA;Box" icon="gray_shulker_box"/>
        <black_shulker_box name="Black&#xA;Shulker&#xA;Box" icon="black_shulker_box"/>
        <shulker_box name="Shulker&#xA;Box" icon="shulker_box"/>
    </shulker_boxes>
    <snow>
        <snow_block name="Snow Block" icon="snow_block"/>
        <powder_snow_bucket name="Powder Snow" icon="powder_snow"/>
        <snow name="Snow" icon="snow"/>
        <ice name="Ice" icon="ice" tags="snow"/>
        <packed_ice name="Packed Ice" icon="packed_ice" tags="snow"/>
        <blue_ice name="Blue Ice" icon="blue_ice" tags="snow"/>
    </snow>
    <specialized>
        <crafting_table name="Crafting Table" icon="crafting_table"/>
        <fletching_table name="Fletching Table" icon="fletching_table" tags="village"/>
        <cartography_table name="Cartography Table" icon="cartography_table" tags="village"/>
        <smithing_table name="Smithing Table" icon="smithing_table" tags="village"/>
        <composter name="Composter" icon="composter" tags="village"/>
        <barrel name="Barrel" icon="barrel" tags="village"/>
        <lectern name="Lectern" icon="lectern_block" tags="village"/>
        <cauldron name="Cauldron" icon="cauldron" tags="village"/>
        <brewing_stand name="Brewing Stand" icon="brewing_stand" tags="village"/>
        <beehive name="Beehive" icon="beehive"/>
        <redstone_lamp name="Redstone Lamp" icon="redstone_lamp"/>

        <furnace name="Furnace" icon="furnace"/>
        <blast_furnace name="Blast Furnace" icon="blast_furnace" tags="village"/>
        <smoker name="Smoker" icon="smoker" tags="village"/>
        <loom name="Loom" icon="loom" tags="village"/>
        <grindstone name="Grindstone" icon="grindstone" tags="village"/>
        <stonecutter name="Stone Cutter" icon="stone_cutter" tags="village"/>
        <bookshelf name="Bookshelf" icon="bookshelf"/>
        <chiseled_bookshelf name="Chiseled Bookshelf" icon="chiseled_bookshelf"/>
        <bell name="Bell" icon="bell" tags="village"/>
        <bee_nest name="Bee Nest" icon="bee_nest"/>
        <daylight_detector name="Daylight Detector" icon="daylight_detector"/>       
 
        <dispenser name="Dispenser" icon="dispenser"/>
        <dropper name="Dropper" icon="dropper"/>
        <observer name="Observer" icon="observer"/>
        <crafter name="Crafter" icon="crafter"/>
        <anvil name="Anvil" icon="anvil" tags="iron"/>
        <chipped_anvil name="Chipped&#xA;Anvil" icon="chipped_anvil" tags="iron"/>
        <damaged_anvil name="Damaged&#xA;Anvil" icon="damaged_anvil" tags="iron"/>
        <enchanting_table name="Enchanting Table" icon="enchanting_table" tags="obsidian diamond book" light_level="0.7"/>
        <beacon name="Beacon" icon="beacon_block" light_level="0.75" tags="obsidian wither"/>
        <honey_block name="Honey Block" icon="honey_block_new" tags="bees"/>
        <target name="Target" icon="target"/>

        <piston name="Piston" icon="piston"/>
        <sticky_piston name="Sticky Piston" icon="sticky_piston"/>
        <hopper name="Hopper" icon="hopper"/>
        <chest name="Chest" icon="chest"/>
        <trapped_chest name="Trapped&#xA;Chest" icon="trapped_chest"/>
        <ender_chest name="Ender&#xA;Chest" icon="ender_chest_block" tags="obsidian endcity"/>
        <repeater name="Redstone&#xA;Repeater" icon="repeater"/>
        <comparator name="Redstone&#xA;Comparator" icon="comparator"/>
        <slime_block name="Slime Block" icon="slime_block_new"/>
        <honeycomb_block name="Honeycomb Block" icon="honeycomb_block" tags="beewax beeswax"/>
        <tnt name="TNT" icon="tnt_block"/>
    </specialized>
    <pots>
        <flower_pot name="Flower Pot" icon="flower_pot"/>
        <decorated_pot name="Decorated Pot" icon="decorated_pot"/>
    </pots>
    <stone>
        <stone name="Stone" icon="stone"/>
        <stone_stairs name="Stone Stairs" icon="stone_stairs"/>
        <empty/>
        <stone_slab name="Stone Slab" icon="stone_slab"/>
    </stone>
    <lichen>
        <glow_lichen name="Glow Lichen" icon="glow_lichen" light_level="0.6"/>
    </lichen>
    <stronghold>
        <stone_bricks name="Stone&#160;Bricks" icon="stone_bricks"/>
        <mossy_stone_bricks name="Mossy&#xA;Stone&#160;Bricks" icon="mossy_stone_bricks"/>
        <cracked_stone_bricks name="Cracked&#xA;Stone&#160;Bricks" icon="cracked_stone_bricks"/>
        <stone_brick_stairs name="Stone&#160;Brick&#xA;Stairs" icon="stone_brick_stairs"/>
        <mossy_stone_brick_stairs name="Mossy&#xA;Stone&#160;Brick&#xA;Stairs" icon="mossy_stone_brick_stairs"/>
        <chiseled_stone_bricks name="Chiseled&#xA;Stone&#160;Bricks" icon="chiseled_stone_bricks"/>
        <stone_brick_slab name="Stone&#160;Brick&#xA;Slab" icon="stone_brick_slab"/>
        <mossy_stone_brick_slab name="Mossy&#xA;Stone&#160;Brick&#xA;Slab" icon="mossy_stone_brick_slab"/>
        <iron_bars name="Iron Bars" icon="iron_bars"/>
        <stone_brick_wall name="Stone&#160;Brick&#xA;Wall" icon="stone_brick_wall"/>
        <mossy_stone_brick_wall name="Mossy&#xA;Stone&#160;Brick&#xA;Wall" icon="mossy_stone_brick_wall"/>
        <end_rod name="End Rod" icon="end_rod" light_level="0.5" tags="endcity"/>
    </stronghold>
    <iron_doors>
        <iron_door name="Iron Door" icon="iron_door" double_height="true"/>
        <iron_trapdoor name="Iron Trapdoor" icon="iron_trapdoor"/>
    </iron_doors>
    <lush>
        <moss_block name="Moss Block" icon="moss_block" tags="lush"/>
        <moss_carpet name="Moss Carpet" icon="moss_carpet" tags="lush"/>
        <azalea_leaves name="Azalea Leaves" icon="azalea_leaves" tags="lush"/>
        <azalea name="Azalea" icon="azalea" tags="lush"/>
        <flowering_azalea_leaves name="Flowering Azalea Leaves" icon="flowering_azalea_leaves" tags="lush"/>
        <flowering_azalea name="Flowering Azalea" icon="flowering_azalea" tags="lush"/>
    </lush>
    <tall_plants>
        <tall_grass name="Tall Grass" icon="tall_grass" double_height="true" tags="village"/>
        <large_fern name="Large Fern" icon="large_fern" double_height="true" tags="village"/>
        <sugar_cane name="Sugarcane" icon="sugarcane_tall" double_height="true"/>
        <cactus name="Cactus" icon="cactus_tall" double_height="true"/>
        <rose_bush name="Rose Bush" icon="rose_bush" double_height="true" tags="flower"/>
        <peony name="Peony" icon="peony" double_height="true" tags="flower"/>
        <lilac name="Lilac" icon="lilac" double_height="true" tags="flower"/>
        <sunflower name="Sunflower" icon="sunflower" double_height="true"/>
        <small_dripleaf name="Small Dripleaf" icon="small_dripleaf" tags="lush" double_height="true"/>
        <big_dripleaf name="Big Dripleaf" icon="big_dripleaf" double_height="true" tags="lush"/>
        <glow_berries name="Cave Vines" icon="cave_vines" double_height="true" tags="lush" light_level="0.7"/>
        <pitcher_plant name="Pitcher Plant" icon="pitcher_plant" double_height="true"/>
    </tall_plants>
    <terracotta>
        <terracotta name="Terracotta" icon="terracotta_block"/>
        <white_terracotta name="White Terracotta" icon="white_terracotta"/>
        <red_terracotta name="Red Terracotta" icon="red_terracotta"/>
        <orange_terracotta name="Orange Terracotta" icon="orange_terracotta"/>
        <yellow_terracotta name="Yellow Terracotta" icon="yellow_terracotta"/>
        <lime_terracotta name="Lime Terracotta" icon="lime_terracotta"/>
        <green_terracotta name="Green Terracotta" icon="green_terracotta"/>
        <cyan_terracotta name="Cyan Terracotta" icon="cyan_terracotta"/>
        <light_blue_terracotta name="Light Blue Terracotta" icon="light_blue_terracotta"/>
        <blue_terracotta name="Blue Terracotta" icon="blue_terracotta"/>
        <purple_terracotta name="Purple Terracotta" icon="purple_terracotta"/>
        <magenta_terracotta name="Magenta Terracotta" icon="magenta_terracotta"/>
        <pink_terracotta name="Pink Terracotta" icon="pink_terracotta"/>
        <brown_terracotta name="Brown Terracotta" icon="brown_terracotta"/>
        <light_gray_terracotta name="Light Gray Terracotta" icon="light_gray_terracotta"/>
        <gray_terracotta name="Gray Terracotta" icon="gray_terracotta"/>
        <black_terracotta name="Black Terracotta" icon="black_terracotta"/>
    </terracotta>
    <vines>
        <vine name="Vine" icon="vine" double_height="true"/>
        <twisting_vines name="Twisting Vines" icon="twisting_vines" double_height="true"/>
        <weeping_vines name="Weeping Vines" icon="weeping_vines" double_height="true"/>
    </vines>
    <wood>
        <oak_log name="Oak&#xA;Log" icon="oak_log"/>
        <oak_wood name="Oak&#xA;Wood" icon="oak_wood"/>
        <stripped_oak_log name="Stripped&#xA;Oak Log" icon="stripped_oak_log"/>
        <stripped_oak_wood name="Stripped&#xA;Oak Wood" icon="stripped_oak_wood"/>
        <oak_planks name="Oak&#xA;Planks" icon="oak_planks"/>
        <oak_stairs name="Oak&#xA;Stairs" icon="oak_stairs"/>
        <oak_slab name="Oak&#xA;Slab" icon="oak_slab"/>
        <oak_fence name="Oak&#xA;Fence" icon="oak_fence"/>
        <oak_fence_gate name="Oak&#xA;Fence Gate" icon="oak_fence_gate"/>
        <oak_trapdoor name="Oak Trapdoor" icon="oak_trapdoor"/>
        <oak_pressure_plate name="Oak&#xA;Pressure Plate" icon="oak_pressure_plate"/>
        <oak_button name="Oak&#xA;Button" icon="oak_button"/>
        <oak_sign name="Oak&#xA;Sign" icon="oak_sign"/>
        <oak_hanging_sign name="Oak&#xA;Hanging&#xA;Sign" icon="oak_hanging_sign"/>
        <spruce_log name="Spruce&#xA;Log" icon="spruce_log"/>
        <spruce_wood name="Spruce&#xA;Wood" icon="spruce_wood"/>
        <stripped_spruce_log name="Stripped&#xA;Spruce Log" icon="stripped_spruce_log"/>
        <stripped_spruce_wood name="Stripped&#xA;Spruce Wood" icon="stripped_spruce_wood"/>
        <spruce_planks name="Spruce&#xA;Planks" icon="spruce_planks"/>
        <spruce_stairs name="Spruce&#xA;Stairs" icon="spruce_stairs"/>
        <spruce_slab name="Spruce&#xA;Slab" icon="spruce_slab"/>
        <spruce_fence name="Spruce&#xA;Fence" icon="spruce_fence"/>
        <spruce_fence_gate name="Spruce&#xA;Fence Gate" icon="spruce_fence_gate"/>
        <spruce_trapdoor name="Spruce Trapdoor" icon="spruce_trapdoor"/>
        <spruce_pressure_plate name="Spruce&#xA;Pressure Plate" icon="spruce_pressure_plate"/>
        <spruce_button name="Spruce&#xA;Button" icon="spruce_button"/>
        <spruce_sign name="Spruce&#xA;Sign" icon="spruce_sign"/>
        <spruce_hanging_sign name="Spruce&#xA;Hanging&#xA;Sign" icon="spruce_hanging_sign"/>
        <birch_log name="Birch&#xA;Log" icon="birch_log"/>
        <birch_wood name="Birch&#xA;Wood" icon="birch_wood"/>
        <stripped_birch_log name="Stripped&#xA;Birch Log" icon="stripped_birch_log"/>
        <stripped_birch_wood name="Stripped&#xA;Birch Wood" icon="stripped_birch_wood"/>
        <birch_planks name="Birch&#xA;Planks" icon="birch_planks"/>
        <birch_stairs name="Birch&#xA;Stairs" icon="birch_stairs"/>
        <birch_slab name="Birch&#xA;Slab" icon="birch_slab"/>
        <birch_fence name="Birch&#xA;Fence" icon="birch_fence"/>
        <birch_fence_gate name="Birch&#xA;Fence Gate" icon="birch_fence_gate"/>
        <birch_trapdoor name="Birch Trapdoor" icon="birch_trapdoor"/>
        <birch_pressure_plate name="Birch&#xA;Pressure Plate" icon="birch_pressure_plate"/>
        <birch_button name="Birch&#xA;Button" icon="birch_button"/>
        <birch_sign name="Birch&#xA;Sign" icon="birch_sign"/>
        <birch_hanging_sign name="Birch&#xA;Hanging&#xA;Sign" icon="birch_hanging_sign"/>
        <jungle_log name="Jungle&#xA;Log" icon="jungle_log"/>
        <jungle_wood name="Jungle&#xA;Wood" icon="jungle_wood"/>
        <stripped_jungle_log name="Stripped&#xA;Jungle Log" icon="stripped_jungle_log"/>
        <stripped_jungle_wood name="Stripped&#xA;Jungle Wood" icon="stripped_jungle_wood"/>
        <jungle_planks name="Jungle&#xA;Planks" icon="jungle_planks"/>
        <jungle_stairs name="Jungle&#xA;Stairs" icon="jungle_stairs"/>
        <jungle_slab name="Jungle&#xA;Slab" icon="jungle_slab"/>
        <jungle_fence name="Jungle&#xA;Fence" icon="jungle_fence"/>
        <jungle_fence_gate name="Jungle&#xA;Fence Gate" icon="jungle_fence_gate"/>
        <jungle_trapdoor name="Jungle Trapdoor" icon="jungle_trapdoor"/>
        <jungle_pressure_plate name="Jungle&#xA;Pressure Plate" icon="jungle_pressure_plate"/>
        <jungle_button name="Jungle&#xA;Button" icon="jungle_button"/>
        <jungle_sign name="Jungle&#xA;Sign" icon="jungle_sign"/>
        <jungle_hanging_sign name="Jungle&#xA;Hanging&#xA;Sign" icon="jungle_hanging_sign"/>
        <acacia_log name="Acacia&#xA;Log" icon="acacia_log"/>
        <acacia_wood name="Acacia&#xA;Wood" icon="acacia_wood"/>
        <stripped_acacia_log name="Stripped&#xA;Acacia Log" icon="stripped_acacia_log"/>
        <stripped_acacia_wood name="Stripped&#xA;Acacia Wood" icon="stripped_acacia_wood"/>
        <acacia_planks name="Acacia&#xA;Planks" icon="acacia_planks"/>
        <acacia_stairs name="Acacia&#xA;Stairs" icon="acacia_stairs"/>
        <acacia_slab name="Acacia&#xA;Slab" icon="acacia_slab"/>
        <acacia_fence name="Acacia&#xA;Fence" icon="acacia_fence"/>
        <acacia_fence_gate name="Acacia&#xA;Fence Gate" icon="acacia_fence_gate"/>
        <acacia_trapdoor name="Acacia Trapdoor" icon="acacia_trapdoor"/>
        <acacia_pressure_plate name="Acacia&#xA;Pressure Plate" icon="acacia_pressure_plate"/>
        <acacia_button name="Acacia&#xA;Button" icon="acacia_button"/>
        <acacia_sign name="Acacia&#xA;Sign" icon="acacia_sign"/>
        <acacia_hanging_sign name="Acacia&#xA;Hanging&#xA;Sign" icon="acacia_hanging_sign"/>
        <dark_oak_log name="Dark Oak&#xA;Log" icon="dark_oak_log"/>
        <dark_oak_wood name="Dark Oak&#xA;Wood" icon="dark_oak_wood"/>
        <stripped_dark_oak_log name="Stripped&#xA;Dark Oak Log" icon="stripped_dark_oak_log"/>
        <stripped_dark_oak_wood name="Stripped&#xA;Dark Oak Wood" icon="stripped_dark_oak_wood"/>
        <dark_oak_planks name="Dark Oak&#xA;Planks" icon="dark_oak_planks"/>
        <dark_oak_stairs name="Dark Oak&#xA;Stairs" icon="dark_oak_stairs"/>
        <dark_oak_slab name="Dark Oak&#xA;Slab" icon="dark_oak_slab"/>
        <dark_oak_fence name="Dark Oak&#xA;Fence" icon="dark_oak_fence"/>
        <dark_oak_fence_gate name="Dark Oak&#xA;Fence Gate" icon="dark_oak_fence_gate"/>
        <dark_oak_trapdoor name="Dark Oak Trapdoor" icon="dark_oak_trapdoor"/>
        <dark_oak_pressure_plate name="Dark Oak&#xA;Pressure Plate" icon="dark_oak_pressure_plate"/>
        <dark_oak_button name="Dark Oak&#xA;Button" icon="dark_oak_button"/>
        <dark_oak_sign name="Dark Oak&#xA;Sign" icon="dark_oak_sign"/>
        <dark_oak_hanging_sign name="Dark Oak&#xA;Hanging&#xA;Sign" icon="dark_oak_hanging_sign"/>

        <crimson_stem name="Crimson&#xA;Stem" icon="crimson_stem"/>
        <crimson_hyphae name="Crimson&#xA;Hyphae" icon="crimson_hyphae"/>
        <stripped_crimson_stem name="Stripped&#xA;Crimson Stem" icon="stripped_crimson_stem"/>
        <stripped_crimson_hyphae name="Stripped&#xA;Crimson Hyphae" icon="stripped_crimson_hyphae"/>
        <crimson_planks name="Crimson&#xA;Planks" icon="crimson_planks"/>
        <crimson_stairs name="Crimson&#xA;Stairs" icon="crimson_stairs"/>
        <crimson_slab name="Crimson&#xA;Slab" icon="crimson_slab"/>
        <crimson_fence name="Crimson&#xA;Fence" icon="crimson_fence"/>
        <crimson_fence_gate name="Crimson&#xA;Fence Gate" icon="crimson_fence_gate"/>
        <crimson_trapdoor name="Crimson Trapdoor" icon="crimson_trapdoor"/>
        <crimson_pressure_plate name="Crimson&#xA;Pressure Plate" icon="crimson_pressure_plate"/>
        <crimson_button name="Crimson&#xA;Button" icon="crimson_button"/>
        <crimson_sign name="Crimson&#xA;Sign" icon="crimson_sign"/>
        <crimson_hanging_sign name="Crimson&#xA;Hanging&#xA;Sign" icon="crimson_hanging_sign"/>
        <warped_stem name="Warped&#xA;Stem" icon="warped_stem"/>
        <warped_hyphae name="Warped&#xA;Hyphae" icon="warped_hyphae"/>
        <stripped_warped_stem name="Stripped&#xA;Warped Stem" icon="stripped_warped_stem"/>
        <stripped_warped_hyphae name="Stripped&#xA;Warped Hyphae" icon="stripped_warped_hyphae"/>
        <warped_planks name="Warped&#xA;Planks" icon="warped_planks"/>
        <warped_stairs name="Warped&#xA;Stairs" icon="warped_stairs"/>
        <warped_slab name="Warped&#xA;Slab" icon="warped_slab"/>
        <warped_fence name="Warped&#xA;Fence" icon="warped_fence"/>
        <warped_fence_gate name="Warped&#xA;Fence Gate" icon="warped_fence_gate"/>
        <warped_trapdoor name="Warped Trapdoor" icon="warped_trapdoor"/>
        <warped_pressure_plate name="Warped&#xA;Pressure Plate" icon="warped_pressure_plate"/>
        <warped_button name="Warped&#xA;Button" icon="warped_button"/>
        <warped_sign name="Warped&#xA;Sign" icon="warped_sign"/>
        <warped_hanging_sign name="Warped&#xA;Hanging&#xA;Sign" icon="warped_hanging_sign"/>

        <cherry_log name="Cherry&#xA;Log" icon="cherry_log"/>
        <cherry_wood name="Cherry&#xA;Wood" icon="cherry_wood"/>
        <stripped_cherry_log name="Stripped&#xA;Cherry Log" icon="stripped_cherry_log"/>
        <stripped_cherry_wood name="Stripped&#xA;Cherry Wood" icon="stripped_cherry_wood"/>
        <cherry_planks name="Cherry&#xA;Planks" icon="cherry_planks"/>
        <cherry_stairs name="Cherry&#xA;Stairs" icon="cherry_stairs"/>
        <cherry_slab name="Cherry&#xA;Slab" icon="cherry_slab"/>
        <cherry_fence name="Cherry&#xA;Fence" icon="cherry_fence"/>
        <cherry_fence_gate name="Cherry&#xA;Fence Gate" icon="cherry_fence_gate"/>
        <cherry_trapdoor name="Cherry Trapdoor" icon="cherry_trapdoor"/>
        <cherry_pressure_plate name="Cherry&#xA;Pressure Plate" icon="cherry_pressure_plate"/>
        <cherry_button name="Cherry&#xA;Button" icon="cherry_button"/>
        <cherry_sign name="Cherry&#xA;Sign" icon="cherry_sign"/>
        <cherry_hanging_sign name="Cherry&#xA;Hanging&#xA;Sign" icon="cherry_hanging_sign"/>

        <mangrove_log name="Mangrove&#xA;Log" icon="mangrove_log"/>
        <mangrove_wood name="Mangrove&#xA;Wood" icon="mangrove_wood"/>
        <stripped_mangrove_log name="Stripped&#xA;Mangrove Log" icon="stripped_mangrove_log"/>
        <stripped_mangrove_wood name="Stripped&#xA;Mangrove Wood" icon="stripped_mangrove_wood"/>
        <mangrove_planks name="Mangrove&#xA;Planks" icon="mangrove_planks"/>
        <mangrove_stairs name="Mangrove&#xA;Stairs" icon="mangrove_stairs"/>
        <mangrove_slab name="Mangrove&#xA;Slab" icon="mangrove_slab"/>
        <mangrove_fence name="Mangrove&#xA;Fence" icon="mangrove_fence"/>
        <mangrove_fence_gate name="Mangrove&#xA;Fence Gate" icon="mangrove_fence_gate"/>
        <mangrove_trapdoor name="Mangrove Trapdoor" icon="mangrove_trapdoor"/>
        <mangrove_pressure_plate name="Mangrove&#xA;Pressure Plate" icon="mangrove_pressure_plate"/>
        <mangrove_button name="Mangrove&#xA;Button" icon="mangrove_button"/>
        <mangrove_sign name="Mangrove&#xA;Sign" icon="mangrove_sign"/>
        <mangrove_hanging_sign name="Mangrove&#xA;Hanging&#xA;Sign" icon="mangrove_hanging_sign"/>

        <stripped_bamboo_block name="Stripped&#xA;Bamboo Block" icon="stripped_bamboo_block"/>
        <bamboo_mosaic name="Bamboo&#xA;Mosaic" icon="bamboo_mosaic"/>
        <bamboo_mosaic_stairs name="Bamboo&#xA;Mosaic Stairs" icon="bamboo_mosaic_stairs"/>
        <bamboo_mosaic_slab name="Bamboo&#xA;Mosaic Slab" icon="bamboo_mosaic_slab"/>
        <bamboo_planks name="Bamboo&#xA;Planks" icon="bamboo_planks"/>
        <bamboo_stairs name="Bamboo&#xA;Stairs" icon="bamboo_stairs"/>
        <bamboo_slab name="Bamboo&#xA;Slab" icon="bamboo_slab"/>
        <bamboo_fence name="Bamboo&#xA;Fence" icon="bamboo_fence"/>
        <bamboo_fence_gate name="Bamboo&#xA;Fence Gate" icon="bamboo_fence_gate"/>
        <bamboo_trapdoor name="Bamboo Trapdoor" icon="bamboo_trapdoor"/>
        <bamboo_pressure_plate name="Bamboo&#xA;Pressure Plate" icon="bamboo_pressure_plate"/>
        <bamboo_button name="Bamboo&#xA;Button" icon="bamboo_button"/>
        <bamboo_sign name="Bamboo&#xA;Sign" icon="bamboo_sign"/>
        <bamboo_hanging_sign name="Bamboo&#xA;Hanging&#xA;Sign" icon="bamboo_hanging_sign"/>
    </wood>
    <wool>
        <white_wool name="White&#xA;Wool" icon="white_wool"/>
        <red_wool name="Red&#xA;Wool" icon="red_wool"/>
        <orange_wool name="Orange&#xA;Wool" icon="orange_wool"/>
        <yellow_wool name="Yellow&#xA;Wool" icon="yellow_wool"/>
        <lime_wool name="Lime&#xA;Wool" icon="lime_wool"/>
        <green_wool name="Green&#xA;Wool" icon="green_wool"/>
        <cyan_wool name="Cyan&#xA;Wool" icon="cyan_wool"/>
        <light_blue_wool name="Light Blue&#xA;Wool" icon="light_blue_wool"/>
        <blue_wool name="Blue&#xA;Wool" icon="blue_wool"/>
        <purple_wool name="Purple&#xA;Wool" icon="purple_wool"/>
        <magenta_wool name="Magenta&#xA;Wool" icon="magenta_wool"/>
        <pink_wool name="Pink&#xA;Wool" icon="pink_wool"/>
        <brown_wool name="Brown&#xA;Wool" icon="brown_wool"/>
        <light_gray_wool name="Light Gray&#xA;Wool" icon="light_gray_wool"/>
        <gray_wool name="Gray&#xA;Wool" icon="gray_wool"/>
        <black_wool name="Black&#xA;Wool" icon="black_wool"/>
    </wool>
    <deep_dark>
        <sculk name="Sculk" icon="sculk" light_level="0.6"/>
        <sculk_catalyst name="Sculk&#xA;Catalyst" icon="sculk_catalyst_block" light_level="0.6"/>
        <sculk_shrieker name="Sculk&#xA;Shrieker" icon="sculk_shrieker" light_level="0.6"/>
        <sculk_sensor name="Sculk&#xA;Sensor" icon="sculk_sensor_block" light_level="0.5"/>
        <calibrated_sculk_sensor name="Calibrated&#xA;Sculk&#xA;Sensor" icon="calibrated_sculk_sensor" light_level="0.5"/>
        <sculk_vein name="Sculk&#xA;Vein" icon="sculk_vein" light_level="0.5"/>
    </deep_dark>
    <mud>
        <mud_bricks name="Mud Bricks" icon="mud_bricks"/>
        <mud_brick_stairs name="Mud Brick Stairs" icon="mud_brick_stairs"/>
        <mud_brick_slab name="Mud Brick Slab" icon="mud_brick_slab"/>
        <mud_brick_wall name="Mud Brick Wall" icon="mud_brick_wall"/>
        <packed_mud name="Packed Mud" icon="packed_mud"/>
        <mud name="Mud" icon="mud"/>
        <muddy_mangrove_roots name="Muddy Mangrove Roots" icon="muddy_mangrove_roots"/>
        <mangrove_roots name="Mangrove Roots" icon="mangrove_roots"/>
    </mud>
    <frogs>
        <verdant_froglight name="Verdant&#xA;Froglight" icon="verdant_froglight" light_level="0.6"/>
        <ochre_froglight name="Ochre&#xA;Froglight" icon="ochre_froglight" light_level="0.6"/>
        <pearlescent_froglight name="Pearlescent&#xA;Froglight" icon="pearlescent_froglight" light_level="0.6"/>
    </frogs>
</blocks>