<?xml version="1.0" encoding="utf-8" ?>
<group name="Doors">
    <block id="minecraft:iron_door"             name="Iron Door"            icon="iron_door"        double_height="true"/>
    <block id="minecraft:oak_door"              name="Oak Door"             icon="oak_door"         double_height="true"/>
    <block id="minecraft:spruce_door"           name="Spruce Door"          icon="spruce_door"      double_height="true"/>
    <block id="minecraft:birch_door"            name="Birch Door"           icon="birch_door"       double_height="true"/>
    <block id="minecraft:jungle_door"           name="Jungle Door"          icon="jungle_door"      double_height="true"/>
    <block id="minecraft:acacia_door"           name="Acacia Door"          icon="acacia_door"      double_height="true"/>
    <block id="minecraft:dark_oak_door"         name="Dark Oak Door"        icon="dark_oak_door"    double_height="true"/>
    <block id="minecraft:crimson_door"          name="Crimson Door"         icon="crimson_door"     double_height="true"/>
    <block id="minecraft:warped_door"           name="Warped Door"          icon="warped_door"      double_height="true"/>
</group>